pysshpass/__init__.py
pysshpass/__main__.py
simplenet/__init__.py
simplenet/invtest.py
simplenet/main.py
simplenet/vsn.py
simplenet/cli/__init__.py
simplenet/cli/command_executor.py
simplenet/cli/command_executor2.py
simplenet/cli/data_store.py
simplenet/cli/data_store_broke.py
simplenet/cli/inmemdbexample.py
simplenet/cli/reader.py
simplenet/cli/runner.py
simplenet/cli/simplenet.py
simplenet/cli/ssh_client.py
simplenet/cli/ssh_utils.py
simplenet/cli/lib/__init__.py
simplenet/cli/lib/audit_actions.py
simplenet/cli/lib/audit_loop_actions.py
simplenet/cli/lib/config_actions.py
simplenet/cli/lib/handle_restapi.py
simplenet/cli/lib/handle_restapi_loop.py
simplenet/cli/lib/handle_send_config_loop.py
simplenet/cli/lib/send_command_loop_actions.py
simplenet/cli/lib/send_commands_action.py
simplenet/cli/lib/utils.py
simplenet/gui/__init__.py
simplenet/gui/action_gui.py
simplenet/gui/action_handlers.py
simplenet/gui/action_schema.py
simplenet/gui/driver_loader.py
simplenet/gui/inv.py
simplenet/gui/main_gui.py
simplenet/gui/runner_form.py
simplenet/gui/runner_form_basic.py
simplenet/gui/simplenet_wrapper.py
simplenet/gui/ttp_gui.py
simplenet/gui/validator.py
simplenet/gui/visual_actions.py
simplenet/gui/vsndebug.py
simplenet/gui/yaml_viewer.py
simplenet/gui/yv.py
simplenet/gui/__pycache__/__init__.cpython-39.pyc
simplenet/gui/__pycache__/action_gui.cpython-39.pyc
simplenet/gui/__pycache__/action_schema.cpython-39.pyc
simplenet/gui/__pycache__/driver_loader.cpython-39.pyc
simplenet/gui/__pycache__/main_gui.cpython-39.pyc
simplenet/gui/__pycache__/runner_form.cpython-39.pyc
simplenet/gui/__pycache__/runner_form_basic.cpython-39.pyc
simplenet/gui/__pycache__/simplenet_wrapper.cpython-39.pyc
simplenet/gui/__pycache__/visual_actions.cpython-39.pyc
simplenet/gui/__pycache__/vsndebug.cpython-39.pyc
simplenet/gui/__pycache__/yaml_viewer.cpython-39.pyc
simplenet/gui/forms/crud.py
simplenet/gui/forms/send_command_editor.py
simplenet/gui/forms/sqltool.py
pysimplenet-0.1.4.dist-info/LICENSE
pysimplenet-0.1.4.dist-info/METADATA
pysimplenet-0.1.4.dist-info/WHEEL
pysimplenet-0.1.4.dist-info/entry_points.txt
pysimplenet-0.1.4.dist-info/top_level.txt
pysimplenet-0.1.4.dist-info/RECORD
