Metadata-Version: 2.1
Name: pysimplenet
Version: 0.1.4
Summary: Pysimplenet, automation tools for network engineers
Home-page: https://github.com/scottpeterman/pysimplenet
Author: Scott Peterman
Author-email: scottpeterman@gmail.com
License: GPLv3
Classifier: Programming Language :: Python :: 3
Classifier: License :: OSI Approved :: GNU General Public License v3 (GPLv3)
Classifier: Operating System :: OS Independent
Requires-Python: >=3.9
License-File: LICENSE
Requires-Dist: backports.tarfile>=1.2.0
Requires-Dist: bcrypt>=4.2.0
Requires-Dist: certifi>=2024.8.30
Requires-Dist: cffi>=1.17.1
Requires-Dist: charset-normalizer>=3.3.2
Requires-Dist: click>=8.1.7
Requires-Dist: colorama>=0.4.6
Requires-Dist: cryptography>=43.0.1
Requires-Dist: docutils>=0.21.2
Requires-Dist: idna>=3.9
Requires-Dist: importlib-metadata>=8.5.0
Requires-Dist: jaraco.classes>=3.4.0
Requires-Dist: jaraco.context>=6.0.1
Requires-Dist: jaraco.functools>=4.0.2
Requires-Dist: jedi>=0.19.1
Requires-Dist: Jinja2>=3.1.4
Requires-Dist: jmespath>=1.0.1
Requires-Dist: keyring>=25.3.0
Requires-Dist: Markdown>=3.7
Requires-Dist: markdown-it-py>=3.0.0
Requires-Dist: MarkupSafe>=2.1.5
Requires-Dist: mdurl>=0.1.2
Requires-Dist: more-itertools>=10.5.0
Requires-Dist: nh3>=0.2.18
Requires-Dist: paramiko>=3.4.1
Requires-Dist: parso>=0.8.4
Requires-Dist: pkginfo>=1.10.0
Requires-Dist: pycparser>=2.22
Requires-Dist: Pygments>=2.18.0
Requires-Dist: PyNaCl>=1.5.0
Requires-Dist: PyQt6>=6.7.1
Requires-Dist: PyQt6-QScintilla>=2.14.1
Requires-Dist: PyQt6-Qt6>=6.7.2
Requires-Dist: PyQt6-sip>=13.8.0
Requires-Dist: pyte>=0.8.2
Requires-Dist: pywin32-ctypes>=0.2.3
Requires-Dist: PyYAML>=6.0.2
Requires-Dist: readme-renderer>=44.0
Requires-Dist: requests>=2.32.3
Requires-Dist: requests-toolbelt>=1.0.0
Requires-Dist: rfc3986>=2.0.0
Requires-Dist: rich>=13.8.1
Requires-Dist: ruamel.yaml>=0.18.6
Requires-Dist: ruamel.yaml.clib>=0.2.8
Requires-Dist: ttp>=0.9.5
Requires-Dist: twine>=5.1.1
Requires-Dist: urllib3>=2.2.3
Requires-Dist: wcwidth>=0.2.13
Requires-Dist: zipp>=3.20.2
